README.md
setup.py
disport/__init__.py
disport/__main__.py
disport/command.py
disport/display.py
disport/disport.py
disport.egg-info/PKG-INFO
disport.egg-info/SOURCES.txt
disport.egg-info/dependency_links.txt
disport.egg-info/entry_points.txt
disport.egg-info/top_level.txt