Metadata-Version: 1.1
Name: disport
Version: 0.1.0
Summary: A xrandr wrapper
Home-page: https://github.com/TimWunderlich/disport
Author: Tim Wunderlich
Author-email: mail@tim-wunderlich.de
License: MIT
Platform: UNKNOWN
Classifier: Programming Language :: Python
Classifier: Programming Language :: Python :: 3.6
